odoo/addons/ecommerce_connector_sii/README.rst
odoo/addons/ecommerce_connector_sii/__init__.py
odoo/addons/ecommerce_connector_sii/__manifest__.py
odoo/addons/ecommerce_connector_sii/models/__init__.py
odoo/addons/ecommerce_connector_sii/models/ecommerce_connector.py
odoo/addons/ecommerce_connector_sii/static/description/icon.png
odoo14_addon_ecommerce_connector_sii-14.0.1.0.0.dist-info/METADATA
odoo14_addon_ecommerce_connector_sii-14.0.1.0.0.dist-info/WHEEL
odoo14_addon_ecommerce_connector_sii-14.0.1.0.0.dist-info/top_level.txt
odoo14_addon_ecommerce_connector_sii-14.0.1.0.0.dist-info/RECORD
