Metadata-Version: 2.1
Name: odoo14-addon-ecommerce_connector_sii
Version: 14.0.1.0.0
Summary: SII values and procedures for ecommerce sale orders.
Author: Sygel
License: AGPL-3
Classifier: Programming Language :: Python
Classifier: Framework :: Odoo
Classifier: Framework :: Odoo :: 14.0
Classifier: License :: OSI Approved :: GNU Affero General Public License v3
Requires-Python: >=3.6
Requires-Dist: odoo14-addon-ecommerce-connector
Requires-Dist: odoo14-addon-l10n-es-aeat-sii-oca
Requires-Dist: odoo<14.1dev,>=14.0a
